<?xml version="1.0" encoding="utf-8"?>
<Tours>
  <Tour Id="1">
    <TourName>Солнечная Турция</TourName>
    <TypeOfAllocation>AI</TypeOfAllocation>
    <Duration>8</Duration>
    <Cost>25000</Cost>
    <Country>Турция</Country>
  </Tour>
  <Tour Id="2">
    <TourName>Достопримечательности Чехии</TourName>
    <TypeOfAllocation>BB</TypeOfAllocation>
    <Duration>7</Duration>
    <Cost>45000</Cost>
    <Country>Чехия</Country>
  </Tour>
  <Tour Id="3">
    <TourName>Дорога открытий</TourName>
    <TypeOfAllocation>RO</TypeOfAllocation>
    <Duration>9</Duration>
    <Cost>50000</Cost>
    <Country>Мексика</Country>
  </Tour>
  <Tour Id="4">
    <TourName>Сердце Грузии</TourName>
    <TypeOfAllocation>AI</TypeOfAllocation>
    <Duration>12</Duration>
    <Cost>40000</Cost>
    <Country>Грузия</Country>
  </Tour>
  <Tour Id="5">
    <TourName>Невероятная Испания</TourName>
    <TypeOfAllocation>BB</TypeOfAllocation>
    <Duration>8</Duration>
    <Cost>45000</Cost>
    <Country>Испания</Country>
  </Tour>
  <Tour Id="6">
    <TourName>Армения</TourName>
    <TypeOfAllocation>BB</TypeOfAllocation>
    <Duration>10</Duration>
    <Cost>35000</Cost>
    <Country>Армения</Country>
  </Tour>
</Tours>